COPYING
COPYING.LESSER
MANIFEST.in
Makefile
README.ipynb
README.md
README.rst
VERSION
requirements.txt
setup.cfg
setup.py
tox.ini
zetuprc
modeled/__init__.py
modeled/adapter.py
modeled/api.py
modeled/base.py
modeled/datetime.py
modeled/dict.py
modeled/extension.py
modeled/list.py
modeled/meta.py
modeled/model.py
modeled/namedtuple.py
modeled/object.py
modeled/options.py
modeled/range.py
modeled/simpledict.py
modeled/tuple.py
modeled/typed.py
modeled/zetup_config.py
modeled.egg-info/PKG-INFO
modeled.egg-info/SOURCES.txt
modeled.egg-info/dependency_links.txt
modeled.egg-info/requires.txt
modeled.egg-info/top_level.txt
modeled/cfunc/__init__.py
modeled/cfunc/arg.py
modeled/cfunc/model.py
modeled/member/__init__.py
modeled/member/context.py
modeled/member/dict.py
modeled/member/handlers.py
modeled/member/list.py
modeled/member/tuple.py
modeled/property/__init__.py
modeled/property/dict.py
modeled/property/list.py
test/test_base.py
test/test_datetime.py
test/test_modeled.py