Metadata-Version: 1.1
Name: modeled
Version: 0.1.8
Summary: Universal data modeling for Python.
Home-page: https://bitbucket.org/userzimmermann/python-modeled
Author: Stefan Zimmermann
Author-email: zimmermann.code@gmail.com
License: LGPLv3
Keywords: modeled,model,modeling,modelled,modelling,serialization,exchange,mapping,class,object,member,property,typed,ctypes,cfunc,funcptr,python3
Platform: UNKNOWN
Classifier: Development Status :: 3 - Alpha
Classifier: Intended Audience :: Developers
Classifier: License :: OSI Approved :: GNU Library or Lesser General Public License (LGPL)
Classifier: Operating System :: OS Independent
Classifier: Topic :: Software Development
Classifier: Topic :: Utilities
Classifier: Programming Language :: Python
Classifier: Programming Language :: Python :: 2.7
Classifier: Programming Language :: Python :: 3.3
Classifier: Programming Language :: Python :: 3.4
